{"warnings":[{"file":"/Users/will3/code/TradeMe/TradeMe/ListingDetailViewController.swift","line":20,"symbol":"Poster","symbol_kind":"source.lang.swift.decl.enumelement","warning":"undocumented"},{"file":"/Users/will3/code/TradeMe/TradeMe/ListingDetailViewController.swift","line":21,"symbol":"Header","symbol_kind":"source.lang.swift.decl.enumelement","warning":"undocumented"},{"file":"/Users/will3/code/TradeMe/TradeMe/ListingDetailViewController.swift","line":22,"symbol":"DetailHeader","symbol_kind":"source.lang.swift.decl.enumelement","warning":"undocumented"},{"file":"/Users/will3/code/TradeMe/TradeMe/ListingDetailViewController.swift","line":23,"symbol":"Details","symbol_kind":"source.lang.swift.decl.enumelement","warning":"undocumented"},{"file":"/Users/will3/code/TradeMe/TradeMe/ListingDetailViewController.swift","line":24,"symbol":"Footer","symbol_kind":"source.lang.swift.decl.enumelement","warning":"undocumented"},{"file":"/Users/will3/code/TradeMe/TradeMe/ListingDetailViewController.swift","line":29,"symbol":"tableView","symbol_kind":"source.lang.swift.decl.var.instance","warning":"undocumented"},{"file":"/Users/will3/code/TradeMe/TradeMe/ListingDetailViewController.swift","line":30,"symbol":"topBar","symbol_kind":"source.lang.swift.decl.var.instance","warning":"undocumented"},{"file":"/Users/will3/code/TradeMe/TradeMe/ListingDetailViewController.swift","line":31,"symbol":"backButton","symbol_kind":"source.lang.swift.decl.var.instance","warning":"undocumented"},{"file":"/Users/will3/code/TradeMe/TradeMe/ListingDetailViewController.swift","line":32,"symbol":"backButton2","symbol_kind":"source.lang.swift.decl.var.instance","warning":"undocumented"},{"file":"/Users/will3/code/TradeMe/TradeMe/ListingDetailViewController.swift","line":37,"symbol":"listing","symbol_kind":"source.lang.swift.decl.var.instance","warning":"undocumented"},{"file":"/Users/will3/code/TradeMe/TradeMe/ListingDetailViewController.swift","line":53,"symbol":"listingService","symbol_kind":"source.lang.swift.decl.var.instance","warning":"undocumented"},{"file":"/Users/will3/code/TradeMe/TradeMe/ListingDetailViewController.swift","line":57,"symbol":"viewDidLoad()","symbol_kind":"source.lang.swift.decl.function.method.instance","warning":"undocumented"},{"file":"/Users/will3/code/TradeMe/TradeMe/ListingDetailViewController.swift","line":97,"symbol":"viewWillAppear(_:)","symbol_kind":"source.lang.swift.decl.function.method.instance","warning":"undocumented"},{"file":"/Users/will3/code/TradeMe/TradeMe/ListingDetailViewController.swift","line":105,"symbol":"onBackPressed(_:)","symbol_kind":"source.lang.swift.decl.function.method.instance","warning":"undocumented"},{"file":"/Users/will3/code/TradeMe/TradeMe/ListingDetailViewController.swift","line":111,"symbol":"numberOfSectionsInTableView(_:)","symbol_kind":"source.lang.swift.decl.function.method.instance","warning":"undocumented"},{"file":"/Users/will3/code/TradeMe/TradeMe/ListingDetailViewController.swift","line":115,"symbol":"tableView(_:numberOfRowsInSection:)","symbol_kind":"source.lang.swift.decl.function.method.instance","warning":"undocumented"},{"file":"/Users/will3/code/TradeMe/TradeMe/ListingDetailViewController.swift","line":132,"symbol":"tableView(_:cellForRowAtIndexPath:)","symbol_kind":"source.lang.swift.decl.function.method.instance","warning":"undocumented"},{"file":"/Users/will3/code/TradeMe/TradeMe/ListingDetailViewController.swift","line":190,"symbol":"cellIdentifierForIndexPath(_:)","symbol_kind":"source.lang.swift.decl.function.method.instance","warning":"undocumented"},{"file":"/Users/will3/code/TradeMe/TradeMe/ListingDetailViewController.swift","line":209,"symbol":"scrollViewDidScroll(_:)","symbol_kind":"source.lang.swift.decl.function.method.instance","warning":"undocumented"},{"file":"/Users/will3/code/TradeMe/TradeMe/StandardDateTransform.swift","line":13,"symbol":"StandardDateTransform","symbol_kind":"source.lang.swift.decl.class","warning":"undocumented"},{"file":"/Users/will3/code/TradeMe/TradeMe/StandardDateTransform.swift","line":14,"symbol":"dateFormatter","symbol_kind":"source.lang.swift.decl.var.static","warning":"undocumented"},{"file":"/Users/will3/code/TradeMe/TradeMe/StandardDateTransform.swift","line":23,"symbol":"transformToJSON(_:)","symbol_kind":"source.lang.swift.decl.function.method.instance","warning":"undocumented"},{"file":"/Users/will3/code/TradeMe/TradeMe/StandardDateTransform.swift","line":31,"symbol":"transformFromJSON(_:)","symbol_kind":"source.lang.swift.decl.function.method.instance","warning":"undocumented"},{"file":"/Users/will3/code/TradeMe/TradeMe/CategoryViewController.swift","line":28,"symbol":"tableView","symbol_kind":"source.lang.swift.decl.var.instance","warning":"undocumented"},{"file":"/Users/will3/code/TradeMe/TradeMe/CategoryViewController.swift","line":58,"symbol":"viewDidLoad()","symbol_kind":"source.lang.swift.decl.function.method.instance","warning":"undocumented"},{"file":"/Users/will3/code/TradeMe/TradeMe/CategoryViewController.swift","line":80,"symbol":"viewWillAppear(_:)","symbol_kind":"source.lang.swift.decl.function.method.instance","warning":"undocumented"},{"file":"/Users/will3/code/TradeMe/TradeMe/CategoryViewController.swift","line":108,"symbol":"viewDidAppear(_:)","symbol_kind":"source.lang.swift.decl.function.method.instance","warning":"undocumented"},{"file":"/Users/will3/code/TradeMe/TradeMe/CategoryViewController.swift","line":116,"symbol":"onDonePressed()","symbol_kind":"source.lang.swift.decl.function.method.instance","warning":"undocumented"},{"file":"/Users/will3/code/TradeMe/TradeMe/CategoryViewController.swift","line":125,"symbol":"numberOfSectionsInTableView(_:)","symbol_kind":"source.lang.swift.decl.function.method.instance","warning":"undocumented"},{"file":"/Users/will3/code/TradeMe/TradeMe/CategoryViewController.swift","line":129,"symbol":"tableView(_:numberOfRowsInSection:)","symbol_kind":"source.lang.swift.decl.function.method.instance","warning":"undocumented"},{"file":"/Users/will3/code/TradeMe/TradeMe/CategoryViewController.swift","line":133,"symbol":"tableView(_:cellForRowAtIndexPath:)","symbol_kind":"source.lang.swift.decl.function.method.instance","warning":"undocumented"},{"file":"/Users/will3/code/TradeMe/TradeMe/CategoryViewController.swift","line":159,"symbol":"tableView(_:didSelectRowAtIndexPath:)","symbol_kind":"source.lang.swift.decl.function.method.instance","warning":"undocumented"},{"file":"/Users/will3/code/TradeMe/TradeMe/CategoryViewController.swift","line":184,"symbol":"tableView(_:heightForRowAtIndexPath:)","symbol_kind":"source.lang.swift.decl.function.method.instance","warning":"undocumented"},{"file":"/Users/will3/code/TradeMe/TradeMe/PromiseManager.swift","line":19,"symbol":"get(_:promiseFactory:)","symbol_kind":"source.lang.swift.decl.function.method.instance","warning":"undocumented"},{"file":"/Users/will3/code/TradeMe/TradeMe/OpenHome.swift","line":14,"symbol":"init(_:)","symbol_kind":"source.lang.swift.decl.function.method.instance","warning":"undocumented"},{"file":"/Users/will3/code/TradeMe/TradeMe/OpenHome.swift","line":15,"symbol":"init()","symbol_kind":"source.lang.swift.decl.function.method.instance","warning":"undocumented"},{"file":"/Users/will3/code/TradeMe/TradeMe/OpenHome.swift","line":16,"symbol":"mapping(_:)","symbol_kind":"source.lang.swift.decl.function.method.instance","warning":"undocumented"},{"file":"/Users/will3/code/TradeMe/TradeMe/OpenHome.swift","line":21,"symbol":"start","symbol_kind":"source.lang.swift.decl.var.instance","warning":"undocumented"},{"file":"/Users/will3/code/TradeMe/TradeMe/OpenHome.swift","line":22,"symbol":"end","symbol_kind":"source.lang.swift.decl.var.instance","warning":"undocumented"},{"file":"/Users/will3/code/TradeMe/TradeMe/AppDelegate.swift","line":16,"symbol":"window","symbol_kind":"source.lang.swift.decl.var.instance","warning":"undocumented"},{"file":"/Users/will3/code/TradeMe/TradeMe/AppDelegate.swift","line":18,"symbol":"application(_:didFinishLaunchingWithOptions:)","symbol_kind":"source.lang.swift.decl.function.method.instance","warning":"undocumented"},{"file":"/Users/will3/code/TradeMe/TradeMe/AppDelegate.swift","line":32,"symbol":"applicationWillResignActive(_:)","symbol_kind":"source.lang.swift.decl.function.method.instance","warning":"undocumented"},{"file":"/Users/will3/code/TradeMe/TradeMe/AppDelegate.swift","line":37,"symbol":"applicationDidEnterBackground(_:)","symbol_kind":"source.lang.swift.decl.function.method.instance","warning":"undocumented"},{"file":"/Users/will3/code/TradeMe/TradeMe/AppDelegate.swift","line":42,"symbol":"applicationWillEnterForeground(_:)","symbol_kind":"source.lang.swift.decl.function.method.instance","warning":"undocumented"},{"file":"/Users/will3/code/TradeMe/TradeMe/AppDelegate.swift","line":46,"symbol":"applicationDidBecomeActive(_:)","symbol_kind":"source.lang.swift.decl.function.method.instance","warning":"undocumented"},{"file":"/Users/will3/code/TradeMe/TradeMe/AppDelegate.swift","line":50,"symbol":"applicationWillTerminate(_:)","symbol_kind":"source.lang.swift.decl.function.method.instance","warning":"undocumented"},{"file":"/Users/will3/code/TradeMe/TradeMe/PhotoUrl.swift","line":14,"symbol":"init(_:)","symbol_kind":"source.lang.swift.decl.function.method.instance","warning":"undocumented"},{"file":"/Users/will3/code/TradeMe/TradeMe/PhotoUrl.swift","line":15,"symbol":"init()","symbol_kind":"source.lang.swift.decl.function.method.instance","warning":"undocumented"},{"file":"/Users/will3/code/TradeMe/TradeMe/PhotoUrl.swift","line":16,"symbol":"mapping(_:)","symbol_kind":"source.lang.swift.decl.function.method.instance","warning":"undocumented"},{"file":"/Users/will3/code/TradeMe/TradeMe/PhotoUrl.swift","line":28,"symbol":"thumbnail","symbol_kind":"source.lang.swift.decl.var.instance","warning":"undocumented"},{"file":"/Users/will3/code/TradeMe/TradeMe/PhotoUrl.swift","line":29,"symbol":"medium","symbol_kind":"source.lang.swift.decl.var.instance","warning":"undocumented"},{"file":"/Users/will3/code/TradeMe/TradeMe/PhotoUrl.swift","line":30,"symbol":"gallery","symbol_kind":"source.lang.swift.decl.var.instance","warning":"undocumented"},{"file":"/Users/will3/code/TradeMe/TradeMe/PhotoUrl.swift","line":31,"symbol":"large","symbol_kind":"source.lang.swift.decl.var.instance","warning":"undocumented"},{"file":"/Users/will3/code/TradeMe/TradeMe/PhotoUrl.swift","line":32,"symbol":"fullSize","symbol_kind":"source.lang.swift.decl.var.instance","warning":"undocumented"},{"file":"/Users/will3/code/TradeMe/TradeMe/PhotoUrl.swift","line":33,"symbol":"plusSize","symbol_kind":"source.lang.swift.decl.var.instance","warning":"undocumented"},{"file":"/Users/will3/code/TradeMe/TradeMe/PhotoUrl.swift","line":34,"symbol":"photoId","symbol_kind":"source.lang.swift.decl.var.instance","warning":"undocumented"},{"file":"/Users/will3/code/TradeMe/TradeMe/PhotoUrl.swift","line":35,"symbol":"originalWidth","symbol_kind":"source.lang.swift.decl.var.instance","warning":"undocumented"},{"file":"/Users/will3/code/TradeMe/TradeMe/PhotoUrl.swift","line":36,"symbol":"originalHeight","symbol_kind":"source.lang.swift.decl.var.instance","warning":"undocumented"},{"file":"/Users/will3/code/TradeMe/TradeMe/ListedItemDetail.swift","line":14,"symbol":"mapping(_:)","symbol_kind":"source.lang.swift.decl.function.method.instance","warning":"undocumented"},{"file":"/Users/will3/code/TradeMe/TradeMe/ListedItemDetail.swift","line":59,"symbol":"bidderAndWatchers","symbol_kind":"source.lang.swift.decl.var.instance","warning":"undocumented"},{"file":"/Users/will3/code/TradeMe/TradeMe/ListedItemDetail.swift","line":60,"symbol":"photoId","symbol_kind":"source.lang.swift.decl.var.instance","warning":"undocumented"},{"file":"/Users/will3/code/TradeMe/TradeMe/ListedItemDetail.swift","line":61,"symbol":"viewCount","symbol_kind":"source.lang.swift.decl.var.instance","warning":"undocumented"},{"file":"/Users/will3/code/TradeMe/TradeMe/ListedItemDetail.swift","line":62,"symbol":"categoryName","symbol_kind":"source.lang.swift.decl.var.instance","warning":"undocumented"},{"file":"/Users/will3/code/TradeMe/TradeMe/ListedItemDetail.swift","line":63,"symbol":"attributes","symbol_kind":"source.lang.swift.decl.var.instance","warning":"undocumented"},{"file":"/Users/will3/code/TradeMe/TradeMe/ListedItemDetail.swift","line":64,"symbol":"relistedItemId","symbol_kind":"source.lang.swift.decl.var.instance","warning":"undocumented"},{"file":"/Users/will3/code/TradeMe/TradeMe/ListedItemDetail.swift","line":65,"symbol":"reservePrice","symbol_kind":"source.lang.swift.decl.var.instance","warning":"undocumented"},{"file":"/Users/will3/code/TradeMe/TradeMe/ListedItemDetail.swift","line":66,"symbol":"hasMultiple","symbol_kind":"source.lang.swift.decl.var.instance","warning":"undocumented"},{"file":"/Users/will3/code/TradeMe/TradeMe/ListedItemDetail.swift","line":67,"symbol":"quantity","symbol_kind":"source.lang.swift.decl.var.instance","warning":"undocumented"},{"file":"/Users/will3/code/TradeMe/TradeMe/ListedItemDetail.swift","line":68,"symbol":"isFlatShippingCharge","symbol_kind":"source.lang.swift.decl.var.instance","warning":"undocumented"},{"file":"/Users/will3/code/TradeMe/TradeMe/ListedItemDetail.swift","line":69,"symbol":"minimumNextBidAmount","symbol_kind":"source.lang.swift.decl.var.instance","warning":"undocumented"},{"file":"/Users/will3/code/TradeMe/TradeMe/ListedItemDetail.swift","line":70,"symbol":"sendPaymentInstructions","symbol_kind":"source.lang.swift.decl.var.instance","warning":"undocumented"},{"file":"/Users/will3/code/TradeMe/TradeMe/ListedItemDetail.swift","line":71,"symbol":"canUsePayNowInstant","symbol_kind":"source.lang.swift.decl.var.instance","warning":"undocumented"},{"file":"/Users/will3/code/TradeMe/TradeMe/ListedItemDetail.swift","line":72,"symbol":"externalReferenceId","symbol_kind":"source.lang.swift.decl.var.instance","warning":"undocumented"},{"file":"/Users/will3/code/TradeMe/TradeMe/ListedItemDetail.swift","line":73,"symbol":"SKU","symbol_kind":"source.lang.swift.decl.var.instance","warning":"undocumented"},{"file":"/Users/will3/code/TradeMe/TradeMe/ListedItemDetail.swift","line":74,"symbol":"availableToBuy","symbol_kind":"source.lang.swift.decl.var.instance","warning":"undocumented"},{"file":"/Users/will3/code/TradeMe/TradeMe/ListedItemDetail.swift","line":75,"symbol":"body","symbol_kind":"source.lang.swift.decl.var.instance","warning":"undocumented"},{"file":"/Users/will3/code/TradeMe/TradeMe/ListedItemDetail.swift","line":76,"symbol":"bids","symbol_kind":"source.lang.swift.decl.var.instance","warning":"undocumented"},{"file":"/Users/will3/code/TradeMe/TradeMe/ListedItemDetail.swift","line":77,"symbol":"questions","symbol_kind":"source.lang.swift.decl.var.instance","warning":"undocumented"},{"file":"/Users/will3/code/TradeMe/TradeMe/ListedItemDetail.swift","line":78,"symbol":"photos","symbol_kind":"source.lang.swift.decl.var.instance","warning":"undocumented"},{"file":"/Users/will3/code/TradeMe/TradeMe/ListedItemDetail.swift","line":79,"symbol":"allowsPickups","symbol_kind":"source.lang.swift.decl.var.instance","warning":"undocumented"},{"file":"/Users/will3/code/TradeMe/TradeMe/ListedItemDetail.swift","line":80,"symbol":"shippingOptions","symbol_kind":"source.lang.swift.decl.var.instance","warning":"undocumented"},{"file":"/Users/will3/code/TradeMe/TradeMe/ListedItemDetail.swift","line":81,"symbol":"paymentOptions","symbol_kind":"source.lang.swift.decl.var.instance","warning":"undocumented"},{"file":"/Users/will3/code/TradeMe/TradeMe/ListedItemDetail.swift","line":82,"symbol":"isOrNearOffer","symbol_kind":"source.lang.swift.decl.var.instance","warning":"undocumented"},{"file":"/Users/will3/code/TradeMe/TradeMe/ListedItemDetail.swift","line":83,"symbol":"unansweredQuestionCount","symbol_kind":"source.lang.swift.decl.var.instance","warning":"undocumented"},{"file":"/Users/will3/code/TradeMe/TradeMe/ListedItemDetail.swift","line":84,"symbol":"authenticatedMembersOnly","symbol_kind":"source.lang.swift.decl.var.instance","warning":"undocumented"},{"file":"/Users/will3/code/TradeMe/TradeMe/ListedItemDetail.swift","line":85,"symbol":"offerStatus","symbol_kind":"source.lang.swift.decl.var.instance","warning":"undocumented"},{"file":"/Users/will3/code/TradeMe/TradeMe/ListedItemDetail.swift","line":86,"symbol":"firearmsLicenseRequiredToBuy","symbol_kind":"source.lang.swift.decl.var.instance","warning":"undocumented"},{"file":"/Users/will3/code/TradeMe/TradeMe/ListedItemDetail.swift","line":87,"symbol":"over18DeclarationRequiredToBuy","symbol_kind":"source.lang.swift.decl.var.instance","warning":"undocumented"},{"file":"/Users/will3/code/TradeMe/TradeMe/ListedItemDetail.swift","line":88,"symbol":"canOffer","symbol_kind":"source.lang.swift.decl.var.instance","warning":"undocumented"},{"file":"/Users/will3/code/TradeMe/TradeMe/ListedItemDetail.swift","line":89,"symbol":"canRelist","symbol_kind":"source.lang.swift.decl.var.instance","warning":"undocumented"},{"file":"/Users/will3/code/TradeMe/TradeMe/ListedItemDetail.swift","line":90,"symbol":"withdrawnBySeller","symbol_kind":"source.lang.swift.decl.var.instance","warning":"undocumented"},{"file":"/Users/will3/code/TradeMe/TradeMe/ListedItemDetail.swift","line":91,"symbol":"isInTradeProtected","symbol_kind":"source.lang.swift.decl.var.instance","warning":"undocumented"},{"file":"/Users/will3/code/TradeMe/TradeMe/ListedItemDetail.swift","line":92,"symbol":"isInCart","symbol_kind":"source.lang.swift.decl.var.instance","warning":"undocumented"},{"file":"/Users/will3/code/TradeMe/TradeMe/ListedItemDetail.swift","line":93,"symbol":"isLeading","symbol_kind":"source.lang.swift.decl.var.instance","warning":"undocumented"},{"file":"/Users/will3/code/TradeMe/TradeMe/ListedItemDetail.swift","line":94,"symbol":"isOutbid","symbol_kind":"source.lang.swift.decl.var.instance","warning":"undocumented"},{"file":"/Users/will3/code/TradeMe/TradeMe/ListedItemDetail.swift","line":95,"symbol":"canAddToCart","symbol_kind":"source.lang.swift.decl.var.instance","warning":"undocumented"},{"file":"/Users/will3/code/TradeMe/TradeMe/ListedItemDetail.swift","line":96,"symbol":"cartItemId","symbol_kind":"source.lang.swift.decl.var.instance","warning":"undocumented"},{"file":"/Users/will3/code/TradeMe/TradeMe/ListedItemDetail.swift","line":97,"symbol":"currentAutoBid","symbol_kind":"source.lang.swift.decl.var.instance","warning":"undocumented"},{"file":"/Users/will3/code/TradeMe/TradeMe/ListedItemDetail.swift","line":98,"symbol":"contactCount","symbol_kind":"source.lang.swift.decl.var.instance","warning":"undocumented"},{"file":"/Users/will3/code/TradeMe/TradeMe/Attribute.swift","line":14,"symbol":"init(_:)","symbol_kind":"source.lang.swift.decl.function.method.instance","warning":"undocumented"},{"file":"/Users/will3/code/TradeMe/TradeMe/Attribute.swift","line":15,"symbol":"init()","symbol_kind":"source.lang.swift.decl.function.method.instance","warning":"undocumented"},{"file":"/Users/will3/code/TradeMe/TradeMe/Attribute.swift","line":16,"symbol":"mapping(_:)","symbol_kind":"source.lang.swift.decl.function.method.instance","warning":"undocumented"},{"file":"/Users/will3/code/TradeMe/TradeMe/Attribute.swift","line":26,"symbol":"name","symbol_kind":"source.lang.swift.decl.var.instance","warning":"undocumented"},{"file":"/Users/will3/code/TradeMe/TradeMe/Attribute.swift","line":27,"symbol":"displayName","symbol_kind":"source.lang.swift.decl.var.instance","warning":"undocumented"},{"file":"/Users/will3/code/TradeMe/TradeMe/Attribute.swift","line":28,"symbol":"value","symbol_kind":"source.lang.swift.decl.var.instance","warning":"undocumented"},{"file":"/Users/will3/code/TradeMe/TradeMe/Attribute.swift","line":29,"symbol":"type","symbol_kind":"source.lang.swift.decl.var.instance","warning":"undocumented"},{"file":"/Users/will3/code/TradeMe/TradeMe/Attribute.swift","line":30,"symbol":"range","symbol_kind":"source.lang.swift.decl.var.instance","warning":"undocumented"},{"file":"/Users/will3/code/TradeMe/TradeMe/Attribute.swift","line":31,"symbol":"options","symbol_kind":"source.lang.swift.decl.var.instance","warning":"undocumented"},{"file":"/Users/will3/code/TradeMe/TradeMe/Attribute.swift","line":32,"symbol":"isRequiredForSell","symbol_kind":"source.lang.swift.decl.var.instance","warning":"undocumented"},{"file":"/Users/will3/code/TradeMe/TradeMe/FoundCategory.swift","line":14,"symbol":"init(_:)","symbol_kind":"source.lang.swift.decl.function.method.instance","warning":"undocumented"},{"file":"/Users/will3/code/TradeMe/TradeMe/FoundCategory.swift","line":15,"symbol":"init()","symbol_kind":"source.lang.swift.decl.function.method.instance","warning":"undocumented"},{"file":"/Users/will3/code/TradeMe/TradeMe/FoundCategory.swift","line":16,"symbol":"mapping(_:)","symbol_kind":"source.lang.swift.decl.function.method.instance","warning":"undocumented"},{"file":"/Users/will3/code/TradeMe/TradeMe/FoundCategory.swift","line":23,"symbol":"count","symbol_kind":"source.lang.swift.decl.var.instance","warning":"undocumented"},{"file":"/Users/will3/code/TradeMe/TradeMe/FoundCategory.swift","line":24,"symbol":"category","symbol_kind":"source.lang.swift.decl.var.instance","warning":"undocumented"},{"file":"/Users/will3/code/TradeMe/TradeMe/FoundCategory.swift","line":25,"symbol":"name","symbol_kind":"source.lang.swift.decl.var.instance","warning":"undocumented"},{"file":"/Users/will3/code/TradeMe/TradeMe/FoundCategory.swift","line":26,"symbol":"isRestricted","symbol_kind":"source.lang.swift.decl.var.instance","warning":"undocumented"},{"file":"/Users/will3/code/TradeMe/TradeMe/Questions.swift","line":14,"symbol":"init(_:)","symbol_kind":"source.lang.swift.decl.function.method.instance","warning":"undocumented"},{"file":"/Users/will3/code/TradeMe/TradeMe/Questions.swift","line":15,"symbol":"init()","symbol_kind":"source.lang.swift.decl.function.method.instance","warning":"undocumented"},{"file":"/Users/will3/code/TradeMe/TradeMe/Questions.swift","line":16,"symbol":"mapping(_:)","symbol_kind":"source.lang.swift.decl.function.method.instance","warning":"undocumented"},{"file":"/Users/will3/code/TradeMe/TradeMe/Questions.swift","line":23,"symbol":"totalCount","symbol_kind":"source.lang.swift.decl.var.instance","warning":"undocumented"},{"file":"/Users/will3/code/TradeMe/TradeMe/Questions.swift","line":24,"symbol":"page","symbol_kind":"source.lang.swift.decl.var.instance","warning":"undocumented"},{"file":"/Users/will3/code/TradeMe/TradeMe/Questions.swift","line":25,"symbol":"pageSize","symbol_kind":"source.lang.swift.decl.var.instance","warning":"undocumented"},{"file":"/Users/will3/code/TradeMe/TradeMe/Questions.swift","line":26,"symbol":"list","symbol_kind":"source.lang.swift.decl.var.instance","warning":"undocumented"},{"file":"/Users/will3/code/TradeMe/TradeMe/AllowsPickups.swift","line":13,"symbol":"None","symbol_kind":"source.lang.swift.decl.enumelement","warning":"undocumented"},{"file":"/Users/will3/code/TradeMe/TradeMe/AllowsPickups.swift","line":14,"symbol":"Allow","symbol_kind":"source.lang.swift.decl.enumelement","warning":"undocumented"},{"file":"/Users/will3/code/TradeMe/TradeMe/AllowsPickups.swift","line":15,"symbol":"Demand","symbol_kind":"source.lang.swift.decl.enumelement","warning":"undocumented"},{"file":"/Users/will3/code/TradeMe/TradeMe/AllowsPickups.swift","line":16,"symbol":"Forbid","symbol_kind":"source.lang.swift.decl.enumelement","warning":"undocumented"},{"file":"/Users/will3/code/TradeMe/TradeMe/EmptyCell.swift","line":14,"symbol":"messageLabel","symbol_kind":"source.lang.swift.decl.var.instance","warning":"undocumented"},{"file":"/Users/will3/code/TradeMe/TradeMe/Branding.swift","line":14,"symbol":"init(_:)","symbol_kind":"source.lang.swift.decl.function.method.instance","warning":"undocumented"},{"file":"/Users/will3/code/TradeMe/TradeMe/Branding.swift","line":15,"symbol":"init()","symbol_kind":"source.lang.swift.decl.function.method.instance","warning":"undocumented"},{"file":"/Users/will3/code/TradeMe/TradeMe/Branding.swift","line":16,"symbol":"mapping(_:)","symbol_kind":"source.lang.swift.decl.function.method.instance","warning":"undocumented"},{"file":"/Users/will3/code/TradeMe/TradeMe/Branding.swift","line":21,"symbol":"largeSquareLogo","symbol_kind":"source.lang.swift.decl.var.instance","warning":"undocumented"},{"file":"/Users/will3/code/TradeMe/TradeMe/Branding.swift","line":22,"symbol":"largeWideLogo","symbol_kind":"source.lang.swift.decl.var.instance","warning":"undocumented"},{"file":"/Users/will3/code/TradeMe/TradeMe/HomeViewController.swift","line":26,"symbol":"tableView","symbol_kind":"source.lang.swift.decl.var.instance","warning":"undocumented"},{"file":"/Users/will3/code/TradeMe/TradeMe/HomeViewController.swift","line":27,"symbol":"filterButton","symbol_kind":"source.lang.swift.decl.var.instance","warning":"undocumented"},{"file":"/Users/will3/code/TradeMe/TradeMe/HomeViewController.swift","line":32,"symbol":"listingService","symbol_kind":"source.lang.swift.decl.var.instance","warning":"undocumented"},{"file":"/Users/will3/code/TradeMe/TradeMe/HomeViewController.swift","line":34,"symbol":"listingTableController","symbol_kind":"source.lang.swift.decl.var.instance","warning":"undocumented"},{"file":"/Users/will3/code/TradeMe/TradeMe/HomeViewController.swift","line":39,"symbol":"searchBar","symbol_kind":"source.lang.swift.decl.var.instance","warning":"undocumented"},{"file":"/Users/will3/code/TradeMe/TradeMe/HomeViewController.swift","line":41,"symbol":"pageSize","symbol_kind":"source.lang.swift.decl.var.instance","warning":"undocumented"},{"file":"/Users/will3/code/TradeMe/TradeMe/HomeViewController.swift","line":43,"symbol":"page","symbol_kind":"source.lang.swift.decl.var.instance","warning":"undocumented"},{"file":"/Users/will3/code/TradeMe/TradeMe/HomeViewController.swift","line":45,"symbol":"category","symbol_kind":"source.lang.swift.decl.var.instance","warning":"undocumented"},{"file":"/Users/will3/code/TradeMe/TradeMe/HomeViewController.swift","line":47,"symbol":"list","symbol_kind":"source.lang.swift.decl.var.instance","warning":"undocumented"},{"file":"/Users/will3/code/TradeMe/TradeMe/HomeViewController.swift","line":49,"symbol":"injectDependencies","symbol_kind":"source.lang.swift.decl.var.instance","warning":"undocumented"},{"file":"/Users/will3/code/TradeMe/TradeMe/HomeViewController.swift","line":61,"symbol":"searchBarTextThrottle","symbol_kind":"source.lang.swift.decl.var.instance","warning":"undocumented"},{"file":"/Users/will3/code/TradeMe/TradeMe/HomeViewController.swift","line":74,"symbol":"viewDidLoad()","symbol_kind":"source.lang.swift.decl.function.method.instance","warning":"undocumented"},{"file":"/Users/will3/code/TradeMe/TradeMe/HomeViewController.swift","line":142,"symbol":"viewWillAppear(_:)","symbol_kind":"source.lang.swift.decl.function.method.instance","warning":"undocumented"},{"file":"/Users/will3/code/TradeMe/TradeMe/HomeViewController.swift","line":152,"symbol":"viewDidAppear(_:)","symbol_kind":"source.lang.swift.decl.function.method.instance","warning":"undocumented"},{"file":"/Users/will3/code/TradeMe/TradeMe/HomeViewController.swift","line":159,"symbol":"viewDidDisappear(_:)","symbol_kind":"source.lang.swift.decl.function.method.instance","warning":"undocumented"},{"file":"/Users/will3/code/TradeMe/TradeMe/HomeViewController.swift","line":165,"symbol":"prepareForSegue(_:sender:)","symbol_kind":"source.lang.swift.decl.function.method.instance","warning":"undocumented"},{"file":"/Users/will3/code/TradeMe/TradeMe/HomeViewController.swift","line":188,"symbol":"onFilterPressed(_:)","symbol_kind":"source.lang.swift.decl.function.method.instance","warning":"undocumented"},{"file":"/Users/will3/code/TradeMe/TradeMe/HomeViewController.swift","line":199,"symbol":"onRefreshControl()","symbol_kind":"source.lang.swift.decl.function.method.instance","warning":"undocumented"},{"file":"/Users/will3/code/TradeMe/TradeMe/HomeViewController.swift","line":212,"symbol":"keyboardDidShow(_:)","symbol_kind":"source.lang.swift.decl.function.method.instance","warning":"undocumented"},{"file":"/Users/will3/code/TradeMe/TradeMe/HomeViewController.swift","line":223,"symbol":"keyboardDidHide(_:)","symbol_kind":"source.lang.swift.decl.function.method.instance","warning":"undocumented"},{"file":"/Users/will3/code/TradeMe/TradeMe/HomeViewController.swift","line":232,"symbol":"searchBarCancelPressed()","symbol_kind":"source.lang.swift.decl.function.method.instance","warning":"undocumented"},{"file":"/Users/will3/code/TradeMe/TradeMe/HomeViewController.swift","line":238,"symbol":"adaptivePresentationStyleForPresentationController(_:)","symbol_kind":"source.lang.swift.decl.function.method.instance","warning":"undocumented"},{"file":"/Users/will3/code/TradeMe/TradeMe/HomeViewController.swift","line":244,"symbol":"didChooseCategory(_:viewController:)","symbol_kind":"source.lang.swift.decl.function.method.instance","warning":"undocumented"},{"file":"/Users/will3/code/TradeMe/TradeMe/HomeViewController.swift","line":250,"symbol":"didFinishChoosingCategory(_:)","symbol_kind":"source.lang.swift.decl.function.method.instance","warning":"undocumented"},{"file":"/Users/will3/code/TradeMe/TradeMe/HomeViewController.swift","line":256,"symbol":"searchBarSearchButtonClicked(_:)","symbol_kind":"source.lang.swift.decl.function.method.instance","warning":"undocumented"},{"file":"/Users/will3/code/TradeMe/TradeMe/HomeViewController.swift","line":264,"symbol":"searchBarTextDidBeginEditing(_:)","symbol_kind":"source.lang.swift.decl.function.method.instance","warning":"undocumented"},{"file":"/Users/will3/code/TradeMe/TradeMe/HomeViewController.swift","line":268,"symbol":"searchBarTextDidEndEditing(_:)","symbol_kind":"source.lang.swift.decl.function.method.instance","warning":"undocumented"},{"file":"/Users/will3/code/TradeMe/TradeMe/HomeViewController.swift","line":272,"symbol":"searchBar(_:textDidChange:)","symbol_kind":"source.lang.swift.decl.function.method.instance","warning":"undocumented"},{"file":"/Users/will3/code/TradeMe/TradeMe/HomeViewController.swift","line":278,"symbol":"listingTableController(_:didSelectListing:)","symbol_kind":"source.lang.swift.decl.function.method.instance","warning":"undocumented"},{"file":"/Users/will3/code/TradeMe/TradeMe/SearchParameter.swift","line":14,"symbol":"init(_:)","symbol_kind":"source.lang.swift.decl.function.method.instance","warning":"undocumented"},{"file":"/Users/will3/code/TradeMe/TradeMe/SearchParameter.swift","line":15,"symbol":"init()","symbol_kind":"source.lang.swift.decl.function.method.instance","warning":"undocumented"},{"file":"/Users/will3/code/TradeMe/TradeMe/SearchParameter.swift","line":16,"symbol":"mapping(_:)","symbol_kind":"source.lang.swift.decl.function.method.instance","warning":"undocumented"},{"file":"/Users/will3/code/TradeMe/TradeMe/SearchParameter.swift","line":29,"symbol":"displayName","symbol_kind":"source.lang.swift.decl.var.instance","warning":"undocumented"},{"file":"/Users/will3/code/TradeMe/TradeMe/SearchParameter.swift","line":30,"symbol":"name","symbol_kind":"source.lang.swift.decl.var.instance","warning":"undocumented"},{"file":"/Users/will3/code/TradeMe/TradeMe/SearchParameter.swift","line":31,"symbol":"lowerBoundName","symbol_kind":"source.lang.swift.decl.var.instance","warning":"undocumented"},{"file":"/Users/will3/code/TradeMe/TradeMe/SearchParameter.swift","line":32,"symbol":"upperBoundName","symbol_kind":"source.lang.swift.decl.var.instance","warning":"undocumented"},{"file":"/Users/will3/code/TradeMe/TradeMe/SearchParameter.swift","line":33,"symbol":"type","symbol_kind":"source.lang.swift.decl.var.instance","warning":"undocumented"},{"file":"/Users/will3/code/TradeMe/TradeMe/SearchParameter.swift","line":34,"symbol":"allowsMultipleValues","symbol_kind":"source.lang.swift.decl.var.instance","warning":"undocumented"},{"file":"/Users/will3/code/TradeMe/TradeMe/SearchParameter.swift","line":35,"symbol":"mutualExclusionGroup","symbol_kind":"source.lang.swift.decl.var.instance","warning":"undocumented"},{"file":"/Users/will3/code/TradeMe/TradeMe/SearchParameter.swift","line":36,"symbol":"dependentOn","symbol_kind":"source.lang.swift.decl.var.instance","warning":"undocumented"},{"file":"/Users/will3/code/TradeMe/TradeMe/SearchParameter.swift","line":37,"symbol":"externalOptionsKey","symbol_kind":"source.lang.swift.decl.var.instance","warning":"undocumented"},{"file":"/Users/will3/code/TradeMe/TradeMe/SearchParameter.swift","line":38,"symbol":"options","symbol_kind":"source.lang.swift.decl.var.instance","warning":"undocumented"},{"file":"/Users/will3/code/TradeMe/TradeMe/PhotoSize.swift","line":13,"symbol":"Thumbnail","symbol_kind":"source.lang.swift.decl.enumelement","warning":"undocumented"},{"file":"/Users/will3/code/TradeMe/TradeMe/PhotoSize.swift","line":14,"symbol":"List","symbol_kind":"source.lang.swift.decl.enumelement","warning":"undocumented"},{"file":"/Users/will3/code/TradeMe/TradeMe/PhotoSize.swift","line":15,"symbol":"Medium","symbol_kind":"source.lang.swift.decl.enumelement","warning":"undocumented"},{"file":"/Users/will3/code/TradeMe/TradeMe/PhotoSize.swift","line":16,"symbol":"Gallery","symbol_kind":"source.lang.swift.decl.enumelement","warning":"undocumented"},{"file":"/Users/will3/code/TradeMe/TradeMe/PhotoSize.swift","line":17,"symbol":"Large","symbol_kind":"source.lang.swift.decl.enumelement","warning":"undocumented"},{"file":"/Users/will3/code/TradeMe/TradeMe/PhotoSize.swift","line":18,"symbol":"FullSize","symbol_kind":"source.lang.swift.decl.enumelement","warning":"undocumented"},{"file":"/Users/will3/code/TradeMe/TradeMe/BoolTransform.swift","line":20,"symbol":"transformToJSON(_:)","symbol_kind":"source.lang.swift.decl.function.method.instance","warning":"undocumented"},{"file":"/Users/will3/code/TradeMe/TradeMe/BoolTransform.swift","line":24,"symbol":"transformFromJSON(_:)","symbol_kind":"source.lang.swift.decl.function.method.instance","warning":"undocumented"},{"file":"/Users/will3/code/TradeMe/TradeMe/SortOrder+Formatting.swift","line":15,"symbol":"format()","symbol_kind":"source.lang.swift.decl.function.method.instance","warning":"undocumented"},{"file":"/Users/will3/code/TradeMe/TradeMe/ListingDetailCell.swift","line":16,"symbol":"titleLabel","symbol_kind":"source.lang.swift.decl.var.instance","warning":"undocumented"},{"file":"/Users/will3/code/TradeMe/TradeMe/ListingDetailCell.swift","line":17,"symbol":"detailLabel","symbol_kind":"source.lang.swift.decl.var.instance","warning":"undocumented"},{"file":"/Users/will3/code/TradeMe/TradeMe/CategoryCell.swift","line":16,"symbol":"titleLabel","symbol_kind":"source.lang.swift.decl.var.instance","warning":"undocumented"},{"file":"/Users/will3/code/TradeMe/TradeMe/CategoryCell.swift","line":17,"symbol":"detailLabel","symbol_kind":"source.lang.swift.decl.var.instance","warning":"undocumented"},{"file":"/Users/will3/code/TradeMe/TradeMe/TradeMeApi.swift","line":15,"symbol":"TradeMeApiError","symbol_kind":"source.lang.swift.decl.enum","warning":"undocumented"},{"file":"/Users/will3/code/TradeMe/TradeMe/TradeMeApi.swift","line":16,"symbol":"BadData","symbol_kind":"source.lang.swift.decl.enumelement","warning":"undocumented"},{"file":"/Users/will3/code/TradeMe/TradeMe/TradeMeApi.swift","line":23,"symbol":"categoryRootNumber","symbol_kind":"source.lang.swift.decl.var.static","warning":"undocumented"},{"file":"/Users/will3/code/TradeMe/TradeMe/TradeMeApi.swift","line":25,"symbol":"init(hostUrl:)","symbol_kind":"source.lang.swift.decl.function.method.instance","warning":"undocumented"},{"file":"/Users/will3/code/TradeMe/TradeMe/TradeMeApi.swift","line":29,"symbol":"hostUrl","symbol_kind":"source.lang.swift.decl.var.instance","warning":"undocumented"},{"file":"/Users/will3/code/TradeMe/TradeMe/TradeMeApi.swift","line":30,"symbol":"headers","symbol_kind":"source.lang.swift.decl.var.instance","warning":"undocumented"},{"file":"/Users/will3/code/TradeMe/TradeMe/AttributeOption.swift","line":14,"symbol":"init(_:)","symbol_kind":"source.lang.swift.decl.function.method.instance","warning":"undocumented"},{"file":"/Users/will3/code/TradeMe/TradeMe/AttributeOption.swift","line":15,"symbol":"init()","symbol_kind":"source.lang.swift.decl.function.method.instance","warning":"undocumented"},{"file":"/Users/will3/code/TradeMe/TradeMe/AttributeOption.swift","line":16,"symbol":"mapping(_:)","symbol_kind":"source.lang.swift.decl.function.method.instance","warning":"undocumented"},{"file":"/Users/will3/code/TradeMe/TradeMe/AttributeOption.swift","line":21,"symbol":"value","symbol_kind":"source.lang.swift.decl.var.instance","warning":"undocumented"},{"file":"/Users/will3/code/TradeMe/TradeMe/AttributeOption.swift","line":22,"symbol":"display","symbol_kind":"source.lang.swift.decl.var.instance","warning":"undocumented"},{"file":"/Users/will3/code/TradeMe/TradeMe/ShippingOption.swift","line":14,"symbol":"init(_:)","symbol_kind":"source.lang.swift.decl.function.method.instance","warning":"undocumented"},{"file":"/Users/will3/code/TradeMe/TradeMe/ShippingOption.swift","line":15,"symbol":"init()","symbol_kind":"source.lang.swift.decl.function.method.instance","warning":"undocumented"},{"file":"/Users/will3/code/TradeMe/TradeMe/ShippingOption.swift","line":16,"symbol":"mapping(_:)","symbol_kind":"source.lang.swift.decl.function.method.instance","warning":"undocumented"},{"file":"/Users/will3/code/TradeMe/TradeMe/ShippingOption.swift","line":23,"symbol":"type","symbol_kind":"source.lang.swift.decl.var.instance","warning":"undocumented"},{"file":"/Users/will3/code/TradeMe/TradeMe/ShippingOption.swift","line":24,"symbol":"price","symbol_kind":"source.lang.swift.decl.var.instance","warning":"undocumented"},{"file":"/Users/will3/code/TradeMe/TradeMe/ShippingOption.swift","line":25,"symbol":"method","symbol_kind":"source.lang.swift.decl.var.instance","warning":"undocumented"},{"file":"/Users/will3/code/TradeMe/TradeMe/ShippingOption.swift","line":26,"symbol":"shippingId","symbol_kind":"source.lang.swift.decl.var.instance","warning":"undocumented"},{"file":"/Users/will3/code/TradeMe/TradeMe/BidCollection.swift","line":14,"symbol":"init(_:)","symbol_kind":"source.lang.swift.decl.function.method.instance","warning":"undocumented"},{"file":"/Users/will3/code/TradeMe/TradeMe/BidCollection.swift","line":15,"symbol":"init()","symbol_kind":"source.lang.swift.decl.function.method.instance","warning":"undocumented"},{"file":"/Users/will3/code/TradeMe/TradeMe/BidCollection.swift","line":16,"symbol":"mapping(_:)","symbol_kind":"source.lang.swift.decl.function.method.instance","warning":"undocumented"},{"file":"/Users/will3/code/TradeMe/TradeMe/BidCollection.swift","line":22,"symbol":"totalCount","symbol_kind":"source.lang.swift.decl.var.instance","warning":"undocumented"},{"file":"/Users/will3/code/TradeMe/TradeMe/BidCollection.swift","line":23,"symbol":"page","symbol_kind":"source.lang.swift.decl.var.instance","warning":"undocumented"},{"file":"/Users/will3/code/TradeMe/TradeMe/BidCollection.swift","line":24,"symbol":"pageSize","symbol_kind":"source.lang.swift.decl.var.instance","warning":"undocumented"},{"file":"/Users/will3/code/TradeMe/TradeMe/BidCollection.swift","line":25,"symbol":"list","symbol_kind":"source.lang.swift.decl.var.instance","warning":"undocumented"},{"file":"/Users/will3/code/TradeMe/TradeMe/ListingPosterCell.swift","line":16,"symbol":"posterImageView","symbol_kind":"source.lang.swift.decl.var.instance","warning":"undocumented"},{"file":"/Users/will3/code/TradeMe/TradeMe/ListingPosterCell.swift","line":17,"symbol":"overlayView","symbol_kind":"source.lang.swift.decl.var.instance","warning":"undocumented"},{"file":"/Users/will3/code/TradeMe/TradeMe/GetListingDetailRequest.swift","line":14,"symbol":"init(_:)","symbol_kind":"source.lang.swift.decl.function.method.instance","warning":"undocumented"},{"file":"/Users/will3/code/TradeMe/TradeMe/GetListingDetailRequest.swift","line":15,"symbol":"init()","symbol_kind":"source.lang.swift.decl.function.method.instance","warning":"undocumented"},{"file":"/Users/will3/code/TradeMe/TradeMe/GetListingDetailRequest.swift","line":16,"symbol":"mapping(_:)","symbol_kind":"source.lang.swift.decl.function.method.instance","warning":"undocumented"},{"file":"/Users/will3/code/TradeMe/TradeMe/GetListingDetailRequest.swift","line":22,"symbol":"listingId","symbol_kind":"source.lang.swift.decl.var.instance","warning":"undocumented"},{"file":"/Users/will3/code/TradeMe/TradeMe/GetListingDetailRequest.swift","line":23,"symbol":"file_format","symbol_kind":"source.lang.swift.decl.var.instance","warning":"undocumented"},{"file":"/Users/will3/code/TradeMe/TradeMe/GetListingDetailRequest.swift","line":25,"symbol":"increment_view_count","symbol_kind":"source.lang.swift.decl.var.instance","warning":"undocumented"},{"file":"/Users/will3/code/TradeMe/TradeMe/GetListingDetailRequest.swift","line":26,"symbol":"question_limit","symbol_kind":"source.lang.swift.decl.var.instance","warning":"undocumented"},{"file":"/Users/will3/code/TradeMe/TradeMe/GetListingDetailRequest.swift","line":27,"symbol":"return_member_profile","symbol_kind":"source.lang.swift.decl.var.instance","warning":"undocumented"},{"file":"/Users/will3/code/TradeMe/TradeMe/UIColor+Extensions.swift","line":13,"symbol":"init(red:green:blue:)","symbol_kind":"source.lang.swift.decl.function.method.instance","warning":"undocumented"},{"file":"/Users/will3/code/TradeMe/TradeMe/UIColor+Extensions.swift","line":21,"symbol":"init(netHex:)","symbol_kind":"source.lang.swift.decl.function.method.instance","warning":"undocumented"},{"file":"/Users/will3/code/TradeMe/TradeMe/Photo.swift","line":14,"symbol":"init(_:)","symbol_kind":"source.lang.swift.decl.function.method.instance","warning":"undocumented"},{"file":"/Users/will3/code/TradeMe/TradeMe/Photo.swift","line":15,"symbol":"init()","symbol_kind":"source.lang.swift.decl.function.method.instance","warning":"undocumented"},{"file":"/Users/will3/code/TradeMe/TradeMe/Photo.swift","line":16,"symbol":"mapping(_:)","symbol_kind":"source.lang.swift.decl.function.method.instance","warning":"undocumented"},{"file":"/Users/will3/code/TradeMe/TradeMe/Photo.swift","line":21,"symbol":"photoId","symbol_kind":"source.lang.swift.decl.var.instance","warning":"undocumented"},{"file":"/Users/will3/code/TradeMe/TradeMe/Photo.swift","line":22,"symbol":"value","symbol_kind":"source.lang.swift.decl.var.instance","warning":"undocumented"},{"file":"/Users/will3/code/TradeMe/TradeMe/ListingService.swift","line":16,"symbol":"api","symbol_kind":"source.lang.swift.decl.var.instance","warning":"undocumented"},{"file":"/Users/will3/code/TradeMe/TradeMe/ListingService.swift","line":17,"symbol":"cache","symbol_kind":"source.lang.swift.decl.var.instance","warning":"undocumented"},{"file":"/Users/will3/code/TradeMe/TradeMe/ListingService.swift","line":18,"symbol":"promiseManager","symbol_kind":"source.lang.swift.decl.var.instance","warning":"undocumented"},{"file":"/Users/will3/code/TradeMe/TradeMe/ListingService.swift","line":20,"symbol":"init(api:cache:promiseManager:)","symbol_kind":"source.lang.swift.decl.function.method.instance","warning":"undocumented"},{"file":"/Users/will3/code/TradeMe/TradeMe/AttributeRange.swift","line":14,"symbol":"init(_:)","symbol_kind":"source.lang.swift.decl.function.method.instance","warning":"undocumented"},{"file":"/Users/will3/code/TradeMe/TradeMe/AttributeRange.swift","line":15,"symbol":"init()","symbol_kind":"source.lang.swift.decl.function.method.instance","warning":"undocumented"},{"file":"/Users/will3/code/TradeMe/TradeMe/AttributeRange.swift","line":16,"symbol":"mapping(_:)","symbol_kind":"source.lang.swift.decl.function.method.instance","warning":"undocumented"},{"file":"/Users/will3/code/TradeMe/TradeMe/SearchResponse.swift","line":15,"symbol":"init(_:)","symbol_kind":"source.lang.swift.decl.function.method.instance","warning":"undocumented"},{"file":"/Users/will3/code/TradeMe/TradeMe/SearchResponse.swift","line":16,"symbol":"init()","symbol_kind":"source.lang.swift.decl.function.method.instance","warning":"undocumented"},{"file":"/Users/will3/code/TradeMe/TradeMe/SearchResponse.swift","line":17,"symbol":"mapping(_:)","symbol_kind":"source.lang.swift.decl.function.method.instance","warning":"undocumented"},{"file":"/Users/will3/code/TradeMe/TradeMe/SearchResponse.swift","line":30,"symbol":"totalCount","symbol_kind":"source.lang.swift.decl.var.instance","warning":"undocumented"},{"file":"/Users/will3/code/TradeMe/TradeMe/SearchResponse.swift","line":31,"symbol":"page","symbol_kind":"source.lang.swift.decl.var.instance","warning":"undocumented"},{"file":"/Users/will3/code/TradeMe/TradeMe/SearchResponse.swift","line":32,"symbol":"pageSize","symbol_kind":"source.lang.swift.decl.var.instance","warning":"undocumented"},{"file":"/Users/will3/code/TradeMe/TradeMe/SearchResponse.swift","line":33,"symbol":"list","symbol_kind":"source.lang.swift.decl.var.instance","warning":"undocumented"},{"file":"/Users/will3/code/TradeMe/TradeMe/SearchResponse.swift","line":34,"symbol":"didYouMean","symbol_kind":"source.lang.swift.decl.var.instance","warning":"undocumented"},{"file":"/Users/will3/code/TradeMe/TradeMe/SearchResponse.swift","line":35,"symbol":"foundCategories","symbol_kind":"source.lang.swift.decl.var.instance","warning":"undocumented"},{"file":"/Users/will3/code/TradeMe/TradeMe/SearchResponse.swift","line":36,"symbol":"favouriteId","symbol_kind":"source.lang.swift.decl.var.instance","warning":"undocumented"},{"file":"/Users/will3/code/TradeMe/TradeMe/SearchResponse.swift","line":37,"symbol":"favouriteType","symbol_kind":"source.lang.swift.decl.var.instance","warning":"undocumented"},{"file":"/Users/will3/code/TradeMe/TradeMe/SearchResponse.swift","line":38,"symbol":"parameters","symbol_kind":"source.lang.swift.decl.var.instance","warning":"undocumented"},{"file":"/Users/will3/code/TradeMe/TradeMe/SearchResponse.swift","line":39,"symbol":"sortOrders","symbol_kind":"source.lang.swift.decl.var.instance","warning":"undocumented"},{"file":"/Users/will3/code/TradeMe/TradeMe/ListingHeaderCell.swift","line":12,"symbol":"ListingHeaderCell","symbol_kind":"source.lang.swift.decl.class","warning":"undocumented"},{"file":"/Users/will3/code/TradeMe/TradeMe/ListingHeaderCell.swift","line":13,"symbol":"titleLabel","symbol_kind":"source.lang.swift.decl.var.instance","warning":"undocumented"},{"file":"/Users/will3/code/TradeMe/TradeMe/ListingHeaderCell.swift","line":14,"symbol":"priceLabel","symbol_kind":"source.lang.swift.decl.var.instance","warning":"undocumented"},{"file":"/Users/will3/code/TradeMe/TradeMe/ListingHeaderCell.swift","line":15,"symbol":"reserveLabel","symbol_kind":"source.lang.swift.decl.var.instance","warning":"undocumented"},{"file":"/Users/will3/code/TradeMe/TradeMe/ListingHeaderCell.swift","line":null,"symbol":"ListingHeaderCell","symbol_kind":"source.lang.swift.decl.extension","warning":"undocumented"},{"file":"/Users/will3/code/TradeMe/TradeMe/ListingFooterCell.swift","line":16,"symbol":"idLabel","symbol_kind":"source.lang.swift.decl.var.instance","warning":"undocumented"},{"file":"/Users/will3/code/TradeMe/TradeMe/ListingFooterCell.swift","line":17,"symbol":"viewsLabel","symbol_kind":"source.lang.swift.decl.var.instance","warning":"undocumented"},{"file":"/Users/will3/code/TradeMe/TradeMe/ReserveState.swift","line":14,"symbol":"None","symbol_kind":"source.lang.swift.decl.enumelement","warning":"undocumented"},{"file":"/Users/will3/code/TradeMe/TradeMe/ReserveState.swift","line":16,"symbol":"Met","symbol_kind":"source.lang.swift.decl.enumelement","warning":"undocumented"},{"file":"/Users/will3/code/TradeMe/TradeMe/ReserveState.swift","line":18,"symbol":"NotMet","symbol_kind":"source.lang.swift.decl.enumelement","warning":"undocumented"},{"file":"/Users/will3/code/TradeMe/TradeMe/ReserveState.swift","line":20,"symbol":"NotApplicable","symbol_kind":"source.lang.swift.decl.enumelement","warning":"undocumented"},{"file":"/Users/will3/code/TradeMe/TradeMe/HeaderCell.swift","line":14,"symbol":"titleLabel","symbol_kind":"source.lang.swift.decl.var.instance","warning":"undocumented"},{"file":"/Users/will3/code/TradeMe/TradeMe/HeaderCell.swift","line":15,"symbol":"heightConstraint","symbol_kind":"source.lang.swift.decl.var.instance","warning":"undocumented"},{"file":"/Users/will3/code/TradeMe/TradeMe/StatusBar.swift","line":12,"symbol":"StatusBar","symbol_kind":"source.lang.swift.decl.class","warning":"undocumented"},{"file":"/Users/will3/code/TradeMe/TradeMe/StatusBar.swift","line":13,"symbol":"setBackgroundColor(_:)","symbol_kind":"source.lang.swift.decl.function.method.static","warning":"undocumented"},{"file":"/Users/will3/code/TradeMe/TradeMe/ListingCell.swift","line":18,"symbol":"locationLabel","symbol_kind":"source.lang.swift.decl.var.instance","warning":"undocumented"},{"file":"/Users/will3/code/TradeMe/TradeMe/ListingCell.swift","line":19,"symbol":"timeLabel","symbol_kind":"source.lang.swift.decl.var.instance","warning":"undocumented"},{"file":"/Users/will3/code/TradeMe/TradeMe/ListingCell.swift","line":21,"symbol":"descriptionLabel","symbol_kind":"source.lang.swift.decl.var.instance","warning":"undocumented"},{"file":"/Users/will3/code/TradeMe/TradeMe/ListingCell.swift","line":22,"symbol":"posterImageView","symbol_kind":"source.lang.swift.decl.var.instance","warning":"undocumented"},{"file":"/Users/will3/code/TradeMe/TradeMe/ListingCell.swift","line":24,"symbol":"priceLabel","symbol_kind":"source.lang.swift.decl.var.instance","warning":"undocumented"},{"file":"/Users/will3/code/TradeMe/TradeMe/ListingCell.swift","line":25,"symbol":"reserveLabel","symbol_kind":"source.lang.swift.decl.var.instance","warning":"undocumented"},{"file":"/Users/will3/code/TradeMe/TradeMe/ListingCell.swift","line":27,"symbol":"buyNowLabel","symbol_kind":"source.lang.swift.decl.var.instance","warning":"undocumented"},{"file":"/Users/will3/code/TradeMe/TradeMe/ListingCell.swift","line":28,"symbol":"buyNowPriceLabel","symbol_kind":"source.lang.swift.decl.var.instance","warning":"undocumented"},{"file":"/Users/will3/code/TradeMe/TradeMe/ListingCell.swift","line":30,"symbol":"posterWidthConstraint","symbol_kind":"source.lang.swift.decl.var.instance","warning":"undocumented"},{"file":"/Users/will3/code/TradeMe/TradeMe/ListingCell.swift","line":32,"symbol":"currentImageUrl","symbol_kind":"source.lang.swift.decl.var.instance","warning":"undocumented"},{"file":"/Users/will3/code/TradeMe/TradeMe/Listing.swift","line":14,"symbol":"init(_:)","symbol_kind":"source.lang.swift.decl.function.method.instance","warning":"undocumented"},{"file":"/Users/will3/code/TradeMe/TradeMe/Listing.swift","line":15,"symbol":"init()","symbol_kind":"source.lang.swift.decl.function.method.instance","warning":"undocumented"},{"file":"/Users/will3/code/TradeMe/TradeMe/Listing.swift","line":16,"symbol":"mapping(_:)","symbol_kind":"source.lang.swift.decl.function.method.instance","warning":"undocumented"},{"file":"/Users/will3/code/TradeMe/TradeMe/Listing.swift","line":64,"symbol":"listingId","symbol_kind":"source.lang.swift.decl.var.instance","warning":"undocumented"},{"file":"/Users/will3/code/TradeMe/TradeMe/Listing.swift","line":65,"symbol":"title","symbol_kind":"source.lang.swift.decl.var.instance","warning":"undocumented"},{"file":"/Users/will3/code/TradeMe/TradeMe/Listing.swift","line":66,"symbol":"category","symbol_kind":"source.lang.swift.decl.var.instance","warning":"undocumented"},{"file":"/Users/will3/code/TradeMe/TradeMe/Listing.swift","line":67,"symbol":"startPrice","symbol_kind":"source.lang.swift.decl.var.instance","warning":"undocumented"},{"file":"/Users/will3/code/TradeMe/TradeMe/Listing.swift","line":68,"symbol":"buyNowPrice","symbol_kind":"source.lang.swift.decl.var.instance","warning":"undocumented"},{"file":"/Users/will3/code/TradeMe/TradeMe/Listing.swift","line":69,"symbol":"startDate","symbol_kind":"source.lang.swift.decl.var.instance","warning":"undocumented"},{"file":"/Users/will3/code/TradeMe/TradeMe/Listing.swift","line":70,"symbol":"endDate","symbol_kind":"source.lang.swift.decl.var.instance","warning":"undocumented"},{"file":"/Users/will3/code/TradeMe/TradeMe/Listing.swift","line":71,"symbol":"isFeatured","symbol_kind":"source.lang.swift.decl.var.instance","warning":"undocumented"},{"file":"/Users/will3/code/TradeMe/TradeMe/Listing.swift","line":72,"symbol":"hasGallery","symbol_kind":"source.lang.swift.decl.var.instance","warning":"undocumented"},{"file":"/Users/will3/code/TradeMe/TradeMe/Listing.swift","line":73,"symbol":"isBold","symbol_kind":"source.lang.swift.decl.var.instance","warning":"undocumented"},{"file":"/Users/will3/code/TradeMe/TradeMe/Listing.swift","line":74,"symbol":"isHighlighted","symbol_kind":"source.lang.swift.decl.var.instance","warning":"undocumented"},{"file":"/Users/will3/code/TradeMe/TradeMe/Listing.swift","line":75,"symbol":"hasHomePageFeature","symbol_kind":"source.lang.swift.decl.var.instance","warning":"undocumented"},{"file":"/Users/will3/code/TradeMe/TradeMe/Listing.swift","line":76,"symbol":"maxBidAmount","symbol_kind":"source.lang.swift.decl.var.instance","warning":"undocumented"},{"file":"/Users/will3/code/TradeMe/TradeMe/Listing.swift","line":77,"symbol":"asAt","symbol_kind":"source.lang.swift.decl.var.instance","warning":"undocumented"},{"file":"/Users/will3/code/TradeMe/TradeMe/Listing.swift","line":78,"symbol":"categoryPath","symbol_kind":"source.lang.swift.decl.var.instance","warning":"undocumented"},{"file":"/Users/will3/code/TradeMe/TradeMe/Listing.swift","line":79,"symbol":"pictureHref","symbol_kind":"source.lang.swift.decl.var.instance","warning":"undocumented"},{"file":"/Users/will3/code/TradeMe/TradeMe/Listing.swift","line":80,"symbol":"hasPayNow","symbol_kind":"source.lang.swift.decl.var.instance","warning":"undocumented"},{"file":"/Users/will3/code/TradeMe/TradeMe/Listing.swift","line":81,"symbol":"isNew","symbol_kind":"source.lang.swift.decl.var.instance","warning":"undocumented"},{"file":"/Users/will3/code/TradeMe/TradeMe/Listing.swift","line":82,"symbol":"regionId","symbol_kind":"source.lang.swift.decl.var.instance","warning":"undocumented"},{"file":"/Users/will3/code/TradeMe/TradeMe/Listing.swift","line":83,"symbol":"region","symbol_kind":"source.lang.swift.decl.var.instance","warning":"undocumented"},{"file":"/Users/will3/code/TradeMe/TradeMe/Listing.swift","line":84,"symbol":"suburbId","symbol_kind":"source.lang.swift.decl.var.instance","warning":"undocumented"},{"file":"/Users/will3/code/TradeMe/TradeMe/Listing.swift","line":85,"symbol":"suburb","symbol_kind":"source.lang.swift.decl.var.instance","warning":"undocumented"},{"file":"/Users/will3/code/TradeMe/TradeMe/Listing.swift","line":86,"symbol":"bidCount","symbol_kind":"source.lang.swift.decl.var.instance","warning":"undocumented"},{"file":"/Users/will3/code/TradeMe/TradeMe/Listing.swift","line":87,"symbol":"isReserveMet","symbol_kind":"source.lang.swift.decl.var.instance","warning":"undocumented"},{"file":"/Users/will3/code/TradeMe/TradeMe/Listing.swift","line":88,"symbol":"hasReserve","symbol_kind":"source.lang.swift.decl.var.instance","warning":"undocumented"},{"file":"/Users/will3/code/TradeMe/TradeMe/Listing.swift","line":89,"symbol":"hasBuyNow","symbol_kind":"source.lang.swift.decl.var.instance","warning":"undocumented"},{"file":"/Users/will3/code/TradeMe/TradeMe/Listing.swift","line":90,"symbol":"noteDate","symbol_kind":"source.lang.swift.decl.var.instance","warning":"undocumented"},{"file":"/Users/will3/code/TradeMe/TradeMe/Listing.swift","line":91,"symbol":"reserveState","symbol_kind":"source.lang.swift.decl.var.instance","warning":"undocumented"},{"file":"/Users/will3/code/TradeMe/TradeMe/Listing.swift","line":92,"symbol":"isClassified","symbol_kind":"source.lang.swift.decl.var.instance","warning":"undocumented"},{"file":"/Users/will3/code/TradeMe/TradeMe/Listing.swift","line":93,"symbol":"openHomes","symbol_kind":"source.lang.swift.decl.var.instance","warning":"undocumented"},{"file":"/Users/will3/code/TradeMe/TradeMe/Listing.swift","line":94,"symbol":"subtitle","symbol_kind":"source.lang.swift.decl.var.instance","warning":"undocumented"},{"file":"/Users/will3/code/TradeMe/TradeMe/Listing.swift","line":95,"symbol":"isBuyNowOnly","symbol_kind":"source.lang.swift.decl.var.instance","warning":"undocumented"},{"file":"/Users/will3/code/TradeMe/TradeMe/Listing.swift","line":96,"symbol":"remainingGalleryPlusRelists","symbol_kind":"source.lang.swift.decl.var.instance","warning":"undocumented"},{"file":"/Users/will3/code/TradeMe/TradeMe/Listing.swift","line":97,"symbol":"isOnWatchList","symbol_kind":"source.lang.swift.decl.var.instance","warning":"undocumented"},{"file":"/Users/will3/code/TradeMe/TradeMe/Listing.swift","line":98,"symbol":"geographicLocation","symbol_kind":"source.lang.swift.decl.var.instance","warning":"undocumented"},{"file":"/Users/will3/code/TradeMe/TradeMe/Listing.swift","line":99,"symbol":"priceDisplay","symbol_kind":"source.lang.swift.decl.var.instance","warning":"undocumented"},{"file":"/Users/will3/code/TradeMe/TradeMe/Listing.swift","line":100,"symbol":"totalReviewCount","symbol_kind":"source.lang.swift.decl.var.instance","warning":"undocumented"},{"file":"/Users/will3/code/TradeMe/TradeMe/Listing.swift","line":101,"symbol":"positiveReviewCount","symbol_kind":"source.lang.swift.decl.var.instance","warning":"undocumented"},{"file":"/Users/will3/code/TradeMe/TradeMe/Listing.swift","line":102,"symbol":"hasFreeShipping","symbol_kind":"source.lang.swift.decl.var.instance","warning":"undocumented"},{"file":"/Users/will3/code/TradeMe/TradeMe/Listing.swift","line":103,"symbol":"isClearance","symbol_kind":"source.lang.swift.decl.var.instance","warning":"undocumented"},{"file":"/Users/will3/code/TradeMe/TradeMe/Listing.swift","line":104,"symbol":"wasPrice","symbol_kind":"source.lang.swift.decl.var.instance","warning":"undocumented"},{"file":"/Users/will3/code/TradeMe/TradeMe/Listing.swift","line":105,"symbol":"percentageOff","symbol_kind":"source.lang.swift.decl.var.instance","warning":"undocumented"},{"file":"/Users/will3/code/TradeMe/TradeMe/Listing.swift","line":106,"symbol":"branding","symbol_kind":"source.lang.swift.decl.var.instance","warning":"undocumented"},{"file":"/Users/will3/code/TradeMe/TradeMe/Listing.swift","line":107,"symbol":"isSuperFeatured","symbol_kind":"source.lang.swift.decl.var.instance","warning":"undocumented"},{"file":"/Users/will3/code/TradeMe/TradeMe/Question.swift","line":14,"symbol":"init(_:)","symbol_kind":"source.lang.swift.decl.function.method.instance","warning":"undocumented"},{"file":"/Users/will3/code/TradeMe/TradeMe/Question.swift","line":15,"symbol":"init()","symbol_kind":"source.lang.swift.decl.function.method.instance","warning":"undocumented"},{"file":"/Users/will3/code/TradeMe/TradeMe/Question.swift","line":16,"symbol":"mapping(_:)","symbol_kind":"source.lang.swift.decl.function.method.instance","warning":"undocumented"},{"file":"/Users/will3/code/TradeMe/TradeMe/Question.swift","line":26,"symbol":"listingId","symbol_kind":"source.lang.swift.decl.var.instance","warning":"undocumented"},{"file":"/Users/will3/code/TradeMe/TradeMe/Question.swift","line":27,"symbol":"listingQuestionId","symbol_kind":"source.lang.swift.decl.var.instance","warning":"undocumented"},{"file":"/Users/will3/code/TradeMe/TradeMe/Question.swift","line":28,"symbol":"comment","symbol_kind":"source.lang.swift.decl.var.instance","warning":"undocumented"},{"file":"/Users/will3/code/TradeMe/TradeMe/Question.swift","line":29,"symbol":"commentDate","symbol_kind":"source.lang.swift.decl.var.instance","warning":"undocumented"},{"file":"/Users/will3/code/TradeMe/TradeMe/Question.swift","line":30,"symbol":"answer","symbol_kind":"source.lang.swift.decl.var.instance","warning":"undocumented"},{"file":"/Users/will3/code/TradeMe/TradeMe/Question.swift","line":31,"symbol":"answerDate","symbol_kind":"source.lang.swift.decl.var.instance","warning":"undocumented"},{"file":"/Users/will3/code/TradeMe/TradeMe/Question.swift","line":32,"symbol":"isSellerComment","symbol_kind":"source.lang.swift.decl.var.instance","warning":"undocumented"},{"file":"/Users/will3/code/TradeMe/TradeMe/AccessibilityIdentifiers.swift","line":12,"symbol":"AccessibilityIdentifiers","symbol_kind":"source.lang.swift.decl.enum","warning":"undocumented"},{"file":"/Users/will3/code/TradeMe/TradeMe/AccessibilityIdentifiers.swift","line":13,"symbol":"homeView","symbol_kind":"source.lang.swift.decl.enumelement","warning":"undocumented"},{"file":"/Users/will3/code/TradeMe/TradeMe/AccessibilityIdentifiers.swift","line":14,"symbol":"categoryView","symbol_kind":"source.lang.swift.decl.enumelement","warning":"undocumented"},{"file":"/Users/will3/code/TradeMe/TradeMe/AccessibilityIdentifiers.swift","line":15,"symbol":"listingDetailView","symbol_kind":"source.lang.swift.decl.enumelement","warning":"undocumented"},{"file":"/Users/will3/code/TradeMe/TradeMe/AccessibilityIdentifiers.swift","line":17,"symbol":"filterButton","symbol_kind":"source.lang.swift.decl.enumelement","warning":"undocumented"},{"file":"/Users/will3/code/TradeMe/TradeMe/AccessibilityIdentifiers.swift","line":18,"symbol":"searchBar","symbol_kind":"source.lang.swift.decl.enumelement","warning":"undocumented"},{"file":"/Users/will3/code/TradeMe/TradeMe/Category.swift","line":15,"symbol":"name","symbol_kind":"source.lang.swift.decl.var.instance","warning":"undocumented"},{"file":"/Users/will3/code/TradeMe/TradeMe/Category.swift","line":16,"symbol":"number","symbol_kind":"source.lang.swift.decl.var.instance","warning":"undocumented"},{"file":"/Users/will3/code/TradeMe/TradeMe/Category.swift","line":17,"symbol":"path","symbol_kind":"source.lang.swift.decl.var.instance","warning":"undocumented"},{"file":"/Users/will3/code/TradeMe/TradeMe/Category.swift","line":18,"symbol":"subcategories","symbol_kind":"source.lang.swift.decl.var.instance","warning":"undocumented"},{"file":"/Users/will3/code/TradeMe/TradeMe/Category.swift","line":19,"symbol":"count","symbol_kind":"source.lang.swift.decl.var.instance","warning":"undocumented"},{"file":"/Users/will3/code/TradeMe/TradeMe/Category.swift","line":20,"symbol":"hasClassifieds","symbol_kind":"source.lang.swift.decl.var.instance","warning":"undocumented"},{"file":"/Users/will3/code/TradeMe/TradeMe/Category.swift","line":22,"symbol":"init(_:)","symbol_kind":"source.lang.swift.decl.function.method.instance","warning":"undocumented"},{"file":"/Users/will3/code/TradeMe/TradeMe/Category.swift","line":24,"symbol":"init()","symbol_kind":"source.lang.swift.decl.function.method.instance","warning":"undocumented"},{"file":"/Users/will3/code/TradeMe/TradeMe/Category.swift","line":26,"symbol":"mapping(_:)","symbol_kind":"source.lang.swift.decl.function.method.instance","warning":"undocumented"},{"file":"/Users/will3/code/TradeMe/TradeMe/Category.swift","line":37,"symbol":"isRoot","symbol_kind":"source.lang.swift.decl.var.instance","warning":"undocumented"},{"file":"/Users/will3/code/TradeMe/TradeMe/SortOrder.swift","line":13,"symbol":"Default","symbol_kind":"source.lang.swift.decl.enumelement","warning":"undocumented"},{"file":"/Users/will3/code/TradeMe/TradeMe/SortOrder.swift","line":14,"symbol":"FeaturedFirst","symbol_kind":"source.lang.swift.decl.enumelement","warning":"undocumented"},{"file":"/Users/will3/code/TradeMe/TradeMe/SortOrder.swift","line":15,"symbol":"SuperGridFeaturedFirst","symbol_kind":"source.lang.swift.decl.enumelement","warning":"undocumented"},{"file":"/Users/will3/code/TradeMe/TradeMe/SortOrder.swift","line":16,"symbol":"TitleAsc","symbol_kind":"source.lang.swift.decl.enumelement","warning":"undocumented"},{"file":"/Users/will3/code/TradeMe/TradeMe/SortOrder.swift","line":17,"symbol":"ExpiryAsc","symbol_kind":"source.lang.swift.decl.enumelement","warning":"undocumented"},{"file":"/Users/will3/code/TradeMe/TradeMe/SortOrder.swift","line":18,"symbol":"ExpiryDesc","symbol_kind":"source.lang.swift.decl.enumelement","warning":"undocumented"},{"file":"/Users/will3/code/TradeMe/TradeMe/SortOrder.swift","line":19,"symbol":"PriceAsc","symbol_kind":"source.lang.swift.decl.enumelement","warning":"undocumented"},{"file":"/Users/will3/code/TradeMe/TradeMe/SortOrder.swift","line":20,"symbol":"PriceDesc","symbol_kind":"source.lang.swift.decl.enumelement","warning":"undocumented"},{"file":"/Users/will3/code/TradeMe/TradeMe/SortOrder.swift","line":21,"symbol":"BidsMost","symbol_kind":"source.lang.swift.decl.enumelement","warning":"undocumented"},{"file":"/Users/will3/code/TradeMe/TradeMe/SortOrder.swift","line":22,"symbol":"BuyNowAsc","symbol_kind":"source.lang.swift.decl.enumelement","warning":"undocumented"},{"file":"/Users/will3/code/TradeMe/TradeMe/SortOrder.swift","line":23,"symbol":"BuyNowDesc","symbol_kind":"source.lang.swift.decl.enumelement","warning":"undocumented"},{"file":"/Users/will3/code/TradeMe/TradeMe/SortOrder.swift","line":24,"symbol":"ReviewsDesc","symbol_kind":"source.lang.swift.decl.enumelement","warning":"undocumented"},{"file":"/Users/will3/code/TradeMe/TradeMe/SortOrder.swift","line":25,"symbol":"HighestSalary","symbol_kind":"source.lang.swift.decl.enumelement","warning":"undocumented"},{"file":"/Users/will3/code/TradeMe/TradeMe/SortOrder.swift","line":26,"symbol":"LowestSalary","symbol_kind":"source.lang.swift.decl.enumelement","warning":"undocumented"},{"file":"/Users/will3/code/TradeMe/TradeMe/SortOrder.swift","line":27,"symbol":"LowestKilometres","symbol_kind":"source.lang.swift.decl.enumelement","warning":"undocumented"},{"file":"/Users/will3/code/TradeMe/TradeMe/SortOrder.swift","line":28,"symbol":"HighestKilometres","symbol_kind":"source.lang.swift.decl.enumelement","warning":"undocumented"},{"file":"/Users/will3/code/TradeMe/TradeMe/SortOrder.swift","line":29,"symbol":"NewestVehicle","symbol_kind":"source.lang.swift.decl.enumelement","warning":"undocumented"},{"file":"/Users/will3/code/TradeMe/TradeMe/SortOrder.swift","line":30,"symbol":"OldestVehicle","symbol_kind":"source.lang.swift.decl.enumelement","warning":"undocumented"},{"file":"/Users/will3/code/TradeMe/TradeMe/SortOrder.swift","line":31,"symbol":"BestMatch","symbol_kind":"source.lang.swift.decl.enumelement","warning":"undocumented"},{"file":"/Users/will3/code/TradeMe/TradeMe/GeographicLocation.swift","line":14,"symbol":"init(_:)","symbol_kind":"source.lang.swift.decl.function.method.instance","warning":"undocumented"},{"file":"/Users/will3/code/TradeMe/TradeMe/GeographicLocation.swift","line":15,"symbol":"init()","symbol_kind":"source.lang.swift.decl.function.method.instance","warning":"undocumented"},{"file":"/Users/will3/code/TradeMe/TradeMe/GeographicLocation.swift","line":16,"symbol":"mapping(_:)","symbol_kind":"source.lang.swift.decl.function.method.instance","warning":"undocumented"},{"file":"/Users/will3/code/TradeMe/TradeMe/GeographicLocation.swift","line":24,"symbol":"latitude","symbol_kind":"source.lang.swift.decl.var.instance","warning":"undocumented"},{"file":"/Users/will3/code/TradeMe/TradeMe/GeographicLocation.swift","line":25,"symbol":"longitude","symbol_kind":"source.lang.swift.decl.var.instance","warning":"undocumented"},{"file":"/Users/will3/code/TradeMe/TradeMe/GeographicLocation.swift","line":26,"symbol":"northing","symbol_kind":"source.lang.swift.decl.var.instance","warning":"undocumented"},{"file":"/Users/will3/code/TradeMe/TradeMe/GeographicLocation.swift","line":27,"symbol":"easting","symbol_kind":"source.lang.swift.decl.var.instance","warning":"undocumented"},{"file":"/Users/will3/code/TradeMe/TradeMe/GeographicLocation.swift","line":28,"symbol":"accuracy","symbol_kind":"source.lang.swift.decl.var.instance","warning":"undocumented"},{"file":"/Users/will3/code/TradeMe/TradeMe/SearchRequest.swift","line":14,"symbol":"init()","symbol_kind":"source.lang.swift.decl.function.method.instance","warning":"undocumented"},{"file":"/Users/will3/code/TradeMe/TradeMe/SearchRequest.swift","line":15,"symbol":"init(_:)","symbol_kind":"source.lang.swift.decl.function.method.instance","warning":"undocumented"},{"file":"/Users/will3/code/TradeMe/TradeMe/SearchRequest.swift","line":16,"symbol":"mapping(_:)","symbol_kind":"source.lang.swift.decl.function.method.instance","warning":"undocumented"},{"file":"/Users/will3/code/TradeMe/TradeMe/SearchRequest.swift","line":34,"symbol":"buy","symbol_kind":"source.lang.swift.decl.var.instance","warning":"undocumented"},{"file":"/Users/will3/code/TradeMe/TradeMe/SearchRequest.swift","line":35,"symbol":"category","symbol_kind":"source.lang.swift.decl.var.instance","warning":"undocumented"},{"file":"/Users/will3/code/TradeMe/TradeMe/SearchRequest.swift","line":36,"symbol":"clearance","symbol_kind":"source.lang.swift.decl.var.instance","warning":"undocumented"},{"file":"/Users/will3/code/TradeMe/TradeMe/SearchRequest.swift","line":37,"symbol":"condition","symbol_kind":"source.lang.swift.decl.var.instance","warning":"undocumented"},{"file":"/Users/will3/code/TradeMe/TradeMe/SearchRequest.swift","line":38,"symbol":"date_from","symbol_kind":"source.lang.swift.decl.var.instance","warning":"undocumented"},{"file":"/Users/will3/code/TradeMe/TradeMe/SearchRequest.swift","line":39,"symbol":"expired","symbol_kind":"source.lang.swift.decl.var.instance","warning":"undocumented"},{"file":"/Users/will3/code/TradeMe/TradeMe/SearchRequest.swift","line":40,"symbol":"member_listing","symbol_kind":"source.lang.swift.decl.var.instance","warning":"undocumented"},{"file":"/Users/will3/code/TradeMe/TradeMe/SearchRequest.swift","line":41,"symbol":"page","symbol_kind":"source.lang.swift.decl.var.instance","warning":"undocumented"},{"file":"/Users/will3/code/TradeMe/TradeMe/SearchRequest.swift","line":42,"symbol":"pay","symbol_kind":"source.lang.swift.decl.var.instance","warning":"undocumented"},{"file":"/Users/will3/code/TradeMe/TradeMe/SearchRequest.swift","line":43,"symbol":"photo_size","symbol_kind":"source.lang.swift.decl.var.instance","warning":"undocumented"},{"file":"/Users/will3/code/TradeMe/TradeMe/SearchRequest.swift","line":44,"symbol":"return_metadata","symbol_kind":"source.lang.swift.decl.var.instance","warning":"undocumented"},{"file":"/Users/will3/code/TradeMe/TradeMe/SearchRequest.swift","line":45,"symbol":"rows","symbol_kind":"source.lang.swift.decl.var.instance","warning":"undocumented"},{"file":"/Users/will3/code/TradeMe/TradeMe/SearchRequest.swift","line":46,"symbol":"search_string","symbol_kind":"source.lang.swift.decl.var.instance","warning":"undocumented"},{"file":"/Users/will3/code/TradeMe/TradeMe/SearchRequest.swift","line":47,"symbol":"shipping_method","symbol_kind":"source.lang.swift.decl.var.instance","warning":"undocumented"},{"file":"/Users/will3/code/TradeMe/TradeMe/SearchRequest.swift","line":48,"symbol":"sort_order","symbol_kind":"source.lang.swift.decl.var.instance","warning":"undocumented"},{"file":"/Users/will3/code/TradeMe/TradeMe/SearchRequest.swift","line":50,"symbol":"user_district","symbol_kind":"source.lang.swift.decl.var.instance","warning":"undocumented"},{"file":"/Users/will3/code/TradeMe/TradeMe/SearchRequest.swift","line":51,"symbol":"user_region","symbol_kind":"source.lang.swift.decl.var.instance","warning":"undocumented"},{"file":"/Users/will3/code/TradeMe/TradeMe/Bid.swift","line":14,"symbol":"init(_:)","symbol_kind":"source.lang.swift.decl.function.method.instance","warning":"undocumented"},{"file":"/Users/will3/code/TradeMe/TradeMe/Bid.swift","line":15,"symbol":"init()","symbol_kind":"source.lang.swift.decl.function.method.instance","warning":"undocumented"},{"file":"/Users/will3/code/TradeMe/TradeMe/Bid.swift","line":16,"symbol":"mapping(_:)","symbol_kind":"source.lang.swift.decl.function.method.instance","warning":"undocumented"},{"file":"/Users/will3/code/TradeMe/TradeMe/Bid.swift","line":25,"symbol":"account","symbol_kind":"source.lang.swift.decl.var.instance","warning":"undocumented"},{"file":"/Users/will3/code/TradeMe/TradeMe/Bid.swift","line":26,"symbol":"bidAmount","symbol_kind":"source.lang.swift.decl.var.instance","warning":"undocumented"},{"file":"/Users/will3/code/TradeMe/TradeMe/Bid.swift","line":27,"symbol":"isByMobile","symbol_kind":"source.lang.swift.decl.var.instance","warning":"undocumented"},{"file":"/Users/will3/code/TradeMe/TradeMe/Bid.swift","line":28,"symbol":"isByProxy","symbol_kind":"source.lang.swift.decl.var.instance","warning":"undocumented"},{"file":"/Users/will3/code/TradeMe/TradeMe/Bid.swift","line":29,"symbol":"bidDate","symbol_kind":"source.lang.swift.decl.var.instance","warning":"undocumented"},{"file":"/Users/will3/code/TradeMe/TradeMe/Bid.swift","line":30,"symbol":"isBuyNow","symbol_kind":"source.lang.swift.decl.var.instance","warning":"undocumented"},{"file":"/Users/will3/code/TradeMe/TradeMe/CategoryTitleView.swift","line":17,"symbol":"titleLabel","symbol_kind":"source.lang.swift.decl.var.instance","warning":"undocumented"},{"file":"/Users/will3/code/TradeMe/TradeMe/CategoryTitleView.swift","line":18,"symbol":"detailLabel","symbol_kind":"source.lang.swift.decl.var.instance","warning":"undocumented"},{"file":"/Users/will3/code/TradeMe/TradeMe/LoadingCell.swift","line":12,"symbol":"LoadingCell","symbol_kind":"source.lang.swift.decl.class","warning":"undocumented"},{"file":"/Users/will3/code/TradeMe/TradeMe/LoadingCell.swift","line":13,"symbol":"spinner","symbol_kind":"source.lang.swift.decl.var.instance","warning":"undocumented"},{"file":"/Users/will3/code/TradeMe/TradeMe/ListingTableController.swift","line":13,"symbol":"ListingTableControllerDelegate","symbol_kind":"source.lang.swift.decl.protocol","warning":"undocumented"},{"file":"/Users/will3/code/TradeMe/TradeMe/ListingTableController.swift","line":14,"symbol":"listingTableController(_:didSelectListing:)","symbol_kind":"source.lang.swift.decl.function.method.instance","warning":"undocumented"},{"file":"/Users/will3/code/TradeMe/TradeMe/ListingTableController.swift","line":17,"symbol":"ListingTableControllerProtocol","symbol_kind":"source.lang.swift.decl.protocol","warning":"undocumented"},{"file":"/Users/will3/code/TradeMe/TradeMe/ListingTableController.swift","line":18,"symbol":"hookTableView(_:)","symbol_kind":"source.lang.swift.decl.function.method.instance","warning":"undocumented"},{"file":"/Users/will3/code/TradeMe/TradeMe/ListingTableController.swift","line":19,"symbol":"reloadData(_:list:)","symbol_kind":"source.lang.swift.decl.function.method.instance","warning":"undocumented"},{"file":"/Users/will3/code/TradeMe/TradeMe/ListingTableController.swift","line":20,"symbol":"loadMore(_:list:)","symbol_kind":"source.lang.swift.decl.function.method.instance","warning":"undocumented"},{"file":"/Users/will3/code/TradeMe/TradeMe/ListingTableController.swift","line":21,"symbol":"showLoading(_:)","symbol_kind":"source.lang.swift.decl.function.method.instance","warning":"undocumented"},{"file":"/Users/will3/code/TradeMe/TradeMe/ListingTableController.swift","line":22,"symbol":"delegate","symbol_kind":"source.lang.swift.decl.var.instance","warning":"undocumented"},{"file":"/Users/will3/code/TradeMe/TradeMe/ListingTableController.swift","line":23,"symbol":"scrollViewTracker","symbol_kind":"source.lang.swift.decl.var.instance","warning":"undocumented"},{"file":"/Users/will3/code/TradeMe/TradeMe/ListingTableController.swift","line":41,"symbol":"Sections","symbol_kind":"source.lang.swift.decl.enum","warning":"undocumented"},{"file":"/Users/will3/code/TradeMe/TradeMe/ListingTableController.swift","line":42,"symbol":"Status","symbol_kind":"source.lang.swift.decl.enumelement","warning":"undocumented"},{"file":"/Users/will3/code/TradeMe/TradeMe/ListingTableController.swift","line":43,"symbol":"List","symbol_kind":"source.lang.swift.decl.enumelement","warning":"undocumented"},{"file":"/Users/will3/code/TradeMe/TradeMe/ListingTableController.swift","line":44,"symbol":"Loading","symbol_kind":"source.lang.swift.decl.enumelement","warning":"undocumented"},{"file":"/Users/will3/code/TradeMe/TradeMe/ListingTableController.swift","line":48,"symbol":"currencyFormat","symbol_kind":"source.lang.swift.decl.var.instance","warning":"undocumented"},{"file":"/Users/will3/code/TradeMe/TradeMe/ListingTableController.swift","line":51,"symbol":"scrollViewTracker","symbol_kind":"source.lang.swift.decl.var.instance","warning":"undocumented"},{"file":"/Users/will3/code/TradeMe/TradeMe/ListingTableController.swift","line":54,"symbol":"delegate","symbol_kind":"source.lang.swift.decl.var.instance","warning":"undocumented"},{"file":"/Users/will3/code/TradeMe/TradeMe/ListingTableController.swift","line":67,"symbol":"init(currencyFormat:)","symbol_kind":"source.lang.swift.decl.function.method.instance","warning":"undocumented"},{"file":"/Users/will3/code/TradeMe/TradeMe/ListingTableController.swift","line":139,"symbol":"numberOfSectionsInTableView(_:)","symbol_kind":"source.lang.swift.decl.function.method.instance","warning":"undocumented"},{"file":"/Users/will3/code/TradeMe/TradeMe/ListingTableController.swift","line":143,"symbol":"tableView(_:numberOfRowsInSection:)","symbol_kind":"source.lang.swift.decl.function.method.instance","warning":"undocumented"},{"file":"/Users/will3/code/TradeMe/TradeMe/ListingTableController.swift","line":156,"symbol":"tableView(_:cellForRowAtIndexPath:)","symbol_kind":"source.lang.swift.decl.function.method.instance","warning":"undocumented"},{"file":"/Users/will3/code/TradeMe/TradeMe/ListingTableController.swift","line":185,"symbol":"tableView(_:didSelectRowAtIndexPath:)","symbol_kind":"source.lang.swift.decl.function.method.instance","warning":"undocumented"},{"file":"/Users/will3/code/TradeMe/TradeMe/ListingTableController.swift","line":192,"symbol":"tableView(_:heightForFooterInSection:)","symbol_kind":"source.lang.swift.decl.function.method.instance","warning":"undocumented"},{"file":"/Users/will3/code/TradeMe/TradeMe/ListingTableController.swift","line":196,"symbol":"tableView(_:viewForFooterInSection:)","symbol_kind":"source.lang.swift.decl.function.method.instance","warning":"undocumented"},{"file":"/Users/will3/code/TradeMe/TradeMe/ListingTableController.swift","line":201,"symbol":"scrollViewDidScroll(_:)","symbol_kind":"source.lang.swift.decl.function.method.instance","warning":"undocumented"},{"file":"/Users/will3/code/TradeMe/TradeMe/FilterButton.swift","line":14,"symbol":"willMoveToWindow(_:)","symbol_kind":"source.lang.swift.decl.function.method.instance","warning":"undocumented"},{"file":"/Users/will3/code/TradeMe/TradeMe/GetCategoryRequest.swift","line":14,"symbol":"number","symbol_kind":"source.lang.swift.decl.var.instance","warning":"undocumented"},{"file":"/Users/will3/code/TradeMe/TradeMe/GetCategoryRequest.swift","line":15,"symbol":"fileFormat","symbol_kind":"source.lang.swift.decl.var.instance","warning":"undocumented"},{"file":"/Users/will3/code/TradeMe/TradeMe/GetCategoryRequest.swift","line":16,"symbol":"depth","symbol_kind":"source.lang.swift.decl.var.instance","warning":"undocumented"},{"file":"/Users/will3/code/TradeMe/TradeMe/GetCategoryRequest.swift","line":17,"symbol":"region","symbol_kind":"source.lang.swift.decl.var.instance","warning":"undocumented"},{"file":"/Users/will3/code/TradeMe/TradeMe/GetCategoryRequest.swift","line":18,"symbol":"withCounts","symbol_kind":"source.lang.swift.decl.var.instance","warning":"undocumented"},{"file":"/Users/will3/code/TradeMe/TradeMe/GetCategoryRequest.swift","line":20,"symbol":"init()","symbol_kind":"source.lang.swift.decl.function.method.instance","warning":"undocumented"},{"file":"/Users/will3/code/TradeMe/TradeMe/GetCategoryRequest.swift","line":21,"symbol":"init(_:)","symbol_kind":"source.lang.swift.decl.function.method.instance","warning":"undocumented"},{"file":"/Users/will3/code/TradeMe/TradeMe/GetCategoryRequest.swift","line":23,"symbol":"mapping(_:)","symbol_kind":"source.lang.swift.decl.function.method.instance","warning":"undocumented"},{"file":"/Users/will3/code/TradeMe/TradeMe/Listing+Formatting.swift","line":14,"symbol":"formatCondition()","symbol_kind":"source.lang.swift.decl.function.method.instance","warning":"undocumented"},{"file":"/Users/will3/code/TradeMe/TradeMe/Listing+Formatting.swift","line":21,"symbol":"formatReserveState()","symbol_kind":"source.lang.swift.decl.function.method.instance","warning":"undocumented"},{"file":"/Users/will3/code/TradeMe/TradeMe/Listing+Formatting.swift","line":39,"symbol":"formatShippingOptions()","symbol_kind":"source.lang.swift.decl.function.method.instance","warning":"undocumented"},{"file":"/Users/will3/code/TradeMe/TradeMe/Listing+Formatting.swift","line":44,"symbol":"formatPaymentOptions()","symbol_kind":"source.lang.swift.decl.function.method.instance","warning":"undocumented"},{"file":"/Users/will3/code/TradeMe/TradeMe/Listing+Formatting.swift","line":52,"symbol":"formatPickups()","symbol_kind":"source.lang.swift.decl.function.method.instance","warning":"undocumented"}],"source_directory":"/Users/will3/code/TradeMe"}